polars_config_meta-0.3.2.dist-info/METADATA
polars_config_meta-0.3.2.dist-info/WHEEL
polars_config_meta-0.3.2.dist-info/entry_points.txt
polars_config_meta-0.3.2.dist-info/licenses/LICENSE
polars_config_meta/__init__.py
polars_config_meta/diagnostics.py
polars_config_meta/discovery.py
polars_config_meta-0.3.2.dist-info/RECORD
