Metadata-Version: 2.1
Name: polars-config-meta
Version: 0.3.2
Summary: A Polars plugin for persistent DataFrame-level metadata
Author-Email: Louis Maddox <louismmx@gmail.com>
Classifier: Development Status :: 4 - Beta
Classifier: Intended Audience :: Developers
Classifier: License :: OSI Approved :: MIT License
Classifier: Natural Language :: English
Classifier: Operating System :: OS Independent
Classifier: Programming Language :: Python :: 3
Classifier: Programming Language :: Python :: 3.10
Classifier: Programming Language :: Python :: 3.11
Classifier: Programming Language :: Python :: 3.12
Classifier: Programming Language :: Python :: 3.13
Classifier: Programming Language :: Python :: Implementation :: CPython
Classifier: Programming Language :: Python
Project-URL: Homepage, https://github.com/lmmx/polars-config-meta
Project-URL: Repository, https://github.com/lmmx/polars-config-meta.git
Requires-Python: >=3.10
Provides-Extra: polars
Requires-Dist: polars>=1.21.0; extra == "polars"
Provides-Extra: polars-lts-cpu
Requires-Dist: polars-lts-cpu>=1.21.0; extra == "polars-lts-cpu"
Provides-Extra: pyarrow
Requires-Dist: pyarrow>=22.0.0; extra == "pyarrow"
